logger/__init__.py
logger/error.py
logger/handler.py
logger/utils.py
advanced_logger-1.0.0a2.dist-info/METADATA
advanced_logger-1.0.0a2.dist-info/WHEEL
advanced_logger-1.0.0a2.dist-info/top_level.txt
advanced_logger-1.0.0a2.dist-info/RECORD
