Metadata-Version: 2.1
Name: advanced-logger
Version: 1.0.0a2
Author-email: BillLoic <billloic6@gmail.com>
